webinteract
