Metadata-Version: 2.4
Name: webinteract
Version: 1.55
Summary: A Python module for simple web interaction
Home-page: https://www.pg12.org/software
Author: A Andersen
Author-email: a.andersen@pg12.org
License: Modified BSD License
Project-URL: Documentation, https://blog.pg12.org/web-page-interaction-in-python
Project-URL: Download, https://www.pg12.org/dist/py/lib/webinteract/
Classifier: License :: OSI Approved :: BSD License
Classifier: Programming Language :: Python :: 3
Classifier: Operating System :: OS Independent
License-File: LICENSE
Requires-Dist: splinter
Requires-Dist: selenium
Requires-Dist: keyring
Requires-Dist: prompt_toolkit
Requires-Dist: colorama
Dynamic: author
Dynamic: author-email
Dynamic: classifier
Dynamic: description
Dynamic: description-content-type
Dynamic: home-page
Dynamic: license
Dynamic: license-file
Dynamic: project-url
Dynamic: requires-dist
Dynamic: summary
